hmoviessdk/__init__.py
hmoviessdk/movies_client.py
hmoviessdk/movies_config.py
hmoviessdk/schemas/__init__.py
hmoviessdk/schemas/schemas.py
hmoviessdk-0.0.2.dist-info/METADATA
hmoviessdk-0.0.2.dist-info/WHEEL
hmoviessdk-0.0.2.dist-info/top_level.txt
hmoviessdk-0.0.2.dist-info/RECORD
